pyscience11/LICENSE
pyscience11/__init__.py
pyscience11/original_license/MATPLOTLIB_LICENSE
pyscience11/original_license/NUMPY_LICENSE
pyscience11/original_license/SCIPY_LICENSE
pyscience11-0.5.data/headers/matplotlib.h
pyscience11-0.5.data/headers/numpy.h
pyscience11-0.5.data/headers/scipy.h
pyscience11-0.5.data/headers/matplotlib/pyplot.h
pyscience11-0.5.data/headers/numpy/dual.h
pyscience11-0.5.data/headers/numpy/fft.h
pyscience11-0.5.data/headers/numpy/linalg.h
pyscience11-0.5.data/headers/numpy/random.h
pyscience11-0.5.data/headers/scipy/fftpack.h
pyscience11-0.5.data/headers/scipy/integrate.h
pyscience11-0.5.data/headers/scipy/interpolate.h
pyscience11-0.5.data/headers/scipy/io.h
pyscience11-0.5.data/headers/scipy/linalg.h
pyscience11-0.5.data/headers/scipy/ndimage.h
pyscience11-0.5.data/headers/scipy/optimize.h
pyscience11-0.5.data/headers/scipy/signal.h
pyscience11-0.5.data/headers/scipy/spatial.h
pyscience11-0.5.data/headers/scipy/special.h
pyscience11-0.5.data/headers/scipy/stats.h
pyscience11-0.5.data/headers/scipy/io/wavfile.h
pyscience11-0.5.dist-info/DESCRIPTION.rst
pyscience11-0.5.dist-info/METADATA
pyscience11-0.5.dist-info/RECORD
pyscience11-0.5.dist-info/WHEEL
pyscience11-0.5.dist-info/metadata.json
pyscience11-0.5.dist-info/top_level.txt
