Metadata-Version: 2.0
Name: pyscience11
Version: 0.5
Summary: C++11 wrapper for NumPy, SciPy and Matplotlib
Home-page: https://github.com/yokaze/pyscience11
Author: Rue Yokaze
Author-email: yokaze.rue@gmail.com
License: MIT
Keywords: C++,pybind11,numpy,scipy,matplotlib
Platform: UNKNOWN
Classifier: Development Status :: 3 - Alpha
Classifier: Intended Audience :: Science/Research
Classifier: License :: OSI Approved :: MIT License
Classifier: Programming Language :: C++
Classifier: Programming Language :: Python :: 3
Classifier: Programming Language :: Python :: 3.6
